quiele/__init__.py
quiele/ink.py
quiele-0.0.6.dist-info/LICENSE
quiele-0.0.6.dist-info/METADATA
quiele-0.0.6.dist-info/WHEEL
quiele-0.0.6.dist-info/top_level.txt
quiele-0.0.6.dist-info/RECORD
